airflow_dbt_python/__init__.py
airflow_dbt_python/__version__.py
airflow_dbt_python/hooks/__init__.py
airflow_dbt_python/hooks/dbt.py
airflow_dbt_python/hooks/target.py
airflow_dbt_python/hooks/fs/__init__.py
airflow_dbt_python/hooks/fs/gcs.py
airflow_dbt_python/hooks/fs/git.py
airflow_dbt_python/hooks/fs/local.py
airflow_dbt_python/hooks/fs/s3.py
airflow_dbt_python/operators/__init__.py
airflow_dbt_python/operators/dbt.py
airflow_dbt_python/utils/__init__.py
airflow_dbt_python/utils/configs.py
airflow_dbt_python/utils/enums.py
airflow_dbt_python/utils/env.py
airflow_dbt_python/utils/url.py
airflow_dbt_python/utils/version.py
airflow_dbt_python-3.2.3.dist-info/licenses/LICENSE
airflow_dbt_python-3.2.3.dist-info/METADATA
airflow_dbt_python-3.2.3.dist-info/WHEEL
airflow_dbt_python-3.2.3.dist-info/top_level.txt
airflow_dbt_python-3.2.3.dist-info/RECORD
