Metadata-Version: 2.4
Name: airflow-dbt-python
Version: 3.2.3
Summary: A collection of Airflow operators, hooks, and utilities to execute dbt commands
Author-email: Tomás Farías Santana <tomas@tomasfarias.dev>
License-Expression: MIT
Project-URL: repository, https://github.com/tomasfarias/airflow-dbt-python
Project-URL: documentation, https://airflow-dbt-python.readthedocs.io
Classifier: Development Status :: 5 - Production/Stable
Classifier: Intended Audience :: Developers
Classifier: Programming Language :: Python :: 3.10
Classifier: Programming Language :: Python :: 3.11
Classifier: Programming Language :: Python :: 3.12
Classifier: Programming Language :: Python :: 3.13
Requires-Python: <3.14,>=3.10
License-File: LICENSE
Requires-Dist: apache-airflow<4.0,>=2.8; python_version < "3.12"
Requires-Dist: apache-airflow<4.0,>=2.9; python_version >= "3.12" and python_version < "3.13"
Requires-Dist: apache-airflow<4.0,>=3.1; python_version >= "3.13"
Requires-Dist: contextlib-chdir==1.0.2; python_version < "3.11"
Requires-Dist: dbt-core<2.0.0,>=1.8.0
Provides-Extra: airflow-providers
Requires-Dist: apache-airflow-providers-amazon>=3.0.0; extra == "airflow-providers"
Requires-Dist: apache-airflow-providers-google>=11.0.0; extra == "airflow-providers"
Requires-Dist: apache-airflow-providers-ssh>=3.0.0; extra == "airflow-providers"
Provides-Extra: adapters
Requires-Dist: dbt-bigquery<2.0.0,>=1.8.0; extra == "adapters"
Requires-Dist: dbt-redshift<2.0.0,>=1.8.0; extra == "adapters"
Requires-Dist: dbt-postgres<2.0.0,>=1.8.0; extra == "adapters"
Requires-Dist: dbt-snowflake<2.0.0,>=1.8.0; extra == "adapters"
Requires-Dist: dbt-spark[all]<2.0.0,>=1.8.0; extra == "adapters"
Provides-Extra: bigquery
Requires-Dist: dbt-bigquery<2.0.0,>=1.8.0; extra == "bigquery"
Provides-Extra: gcs
Requires-Dist: apache-airflow-providers-google>=11.0.0; extra == "gcs"
Provides-Extra: git
Requires-Dist: apache-airflow-providers-ssh>=3.0.0; extra == "git"
Requires-Dist: dulwich>=0.24.3; extra == "git"
Provides-Extra: postgres
Requires-Dist: dbt-postgres<2.0.0,>=1.8.0; extra == "postgres"
Provides-Extra: redshift
Requires-Dist: dbt-redshift<2.0.0,>=1.8.0; extra == "redshift"
Provides-Extra: s3
Requires-Dist: apache-airflow-providers-amazon>=3.0.0; extra == "s3"
Provides-Extra: snowflake
Requires-Dist: dbt-snowflake<2.0.0,>=1.8.0; extra == "snowflake"
Provides-Extra: spark
Requires-Dist: dbt-spark<2.0.0,>=1.8.0; extra == "spark"
Dynamic: license-file
